cool/__init__.py
cool/apps.py
cool/checks.py
cool/settings.py
cool/urls.py
cool/admin/__init__.py
cool/admin/admin.py
cool/admin/filters.py
cool/admin/theme.py
cool/admin/views.py
cool/admin/widgets.py
cool/core/__init__.py
cool/core/cache.py
cool/core/constants.py
cool/core/deprecation.py
cool/core/utils.py
cool/locale/af/LC_MESSAGES/django.mo
cool/locale/af/LC_MESSAGES/django.po
cool/locale/am/LC_MESSAGES/django.mo
cool/locale/am/LC_MESSAGES/django.po
cool/locale/ar/LC_MESSAGES/django.mo
cool/locale/ar/LC_MESSAGES/django.po
cool/locale/ast/LC_MESSAGES/django.mo
cool/locale/ast/LC_MESSAGES/django.po
cool/locale/az/LC_MESSAGES/django.mo
cool/locale/az/LC_MESSAGES/django.po
cool/locale/be/LC_MESSAGES/django.mo
cool/locale/be/LC_MESSAGES/django.po
cool/locale/bg/LC_MESSAGES/django.mo
cool/locale/bg/LC_MESSAGES/django.po
cool/locale/bn/LC_MESSAGES/django.mo
cool/locale/bn/LC_MESSAGES/django.po
cool/locale/br/LC_MESSAGES/django.mo
cool/locale/br/LC_MESSAGES/django.po
cool/locale/bs/LC_MESSAGES/django.mo
cool/locale/bs/LC_MESSAGES/django.po
cool/locale/ca/LC_MESSAGES/django.mo
cool/locale/ca/LC_MESSAGES/django.po
cool/locale/cs/LC_MESSAGES/django.mo
cool/locale/cs/LC_MESSAGES/django.po
cool/locale/cy/LC_MESSAGES/django.mo
cool/locale/cy/LC_MESSAGES/django.po
cool/locale/da/LC_MESSAGES/django.mo
cool/locale/da/LC_MESSAGES/django.po
cool/locale/de/LC_MESSAGES/django.mo
cool/locale/de/LC_MESSAGES/django.po
cool/locale/dsb/LC_MESSAGES/django.mo
cool/locale/dsb/LC_MESSAGES/django.po
cool/locale/el/LC_MESSAGES/django.mo
cool/locale/el/LC_MESSAGES/django.po
cool/locale/en/LC_MESSAGES/django.mo
cool/locale/en/LC_MESSAGES/django.po
cool/locale/en_AU/LC_MESSAGES/django.mo
cool/locale/en_AU/LC_MESSAGES/django.po
cool/locale/en_GB/LC_MESSAGES/django.mo
cool/locale/en_GB/LC_MESSAGES/django.po
cool/locale/eo/LC_MESSAGES/django.mo
cool/locale/eo/LC_MESSAGES/django.po
cool/locale/es/LC_MESSAGES/django.mo
cool/locale/es/LC_MESSAGES/django.po
cool/locale/es_AR/LC_MESSAGES/django.mo
django_cool-1.3.8.dist-info/licenses/LICENSE
django_cool-1.3.8.dist-info/METADATA
django_cool-1.3.8.dist-info/WHEEL
django_cool-1.3.8.dist-info/top_level.txt
django_cool-1.3.8.dist-info/RECORD
