Metadata-Version: 2.4
Name: django-cool
Version: 1.3.8
Summary: Cool to use for the Django Framework.
Home-page: https://django.cool
Author: 007
Author-email: 007@django.cool
License: BSD-3-Clause
Project-URL: Documentation, https://docs.django.cool/
Project-URL: Source, https://github.com/007gzs/django-cool
Classifier: Development Status :: 5 - Production/Stable
Classifier: Environment :: Web Environment
Classifier: Framework :: Django
Classifier: Framework :: Django :: 2.2
Classifier: Framework :: Django :: 3.0
Classifier: Intended Audience :: Developers
Classifier: License :: OSI Approved :: BSD License
Classifier: Operating System :: OS Independent
Classifier: Programming Language :: Python
Classifier: Programming Language :: Python :: 3
Classifier: Programming Language :: Python :: 3 :: Only
Classifier: Programming Language :: Python :: 3.6
Classifier: Programming Language :: Python :: 3.7
Classifier: Programming Language :: Python :: 3.8
Classifier: Programming Language :: Python :: 3.9
Classifier: Programming Language :: Python :: 3.10
Classifier: Topic :: Internet :: WWW/HTTP
Requires-Python: >=3.6
License-File: LICENSE
Requires-Dist: Django>=2.2
Requires-Dist: djangorestframework
Dynamic: license-file
